raco/__init__.py
raco/algebra.py
raco/catalog.py
raco/clangtestdb.py
raco/compile.py
raco/cpp_datalog_utils.py
raco/dbconn.py
raco/fake_data.py
raco/fakedb.py
raco/from_repr.py
raco/nary_join_rules_test.py
raco/operator_test.py
raco/pipelines.py
raco/platform_tests.py
raco/relation_key.py
raco/replace_with_repr.py
raco/representation.py
raco/rules.py
raco/scheme.py
raco/sparql_tests.py
raco/sqllite_test.py
raco/test_style.py
raco/test_utility.py
raco/tests.py
raco/types.py
raco/utility.py
raco/viz.py
raco/backends/__init__.py
raco/backends/backend_common.py
raco/backends/logical.py
raco/backends/cpp/__init__.py
raco/backends/cpp/cpp.py
raco/backends/cpp/cppcommon.py
raco/backends/myria/__init__.py
raco/backends/myria/catalog.py
raco/backends/myria/connection.py
raco/backends/myria/errors.py
raco/backends/myria/myria.py
raco/backends/myria/parsetab.py
raco/backends/radish/__init__.py
raco/backends/radish/radish.py
raco/backends/sparql/__init__.py
raco/backends/sparql/sparql.py
raco/backends/sql/__init__.py
raco/backends/sql/catalog.py
raco/backends/sql/parsetab.py
raco/backends/sql/test_case.py
raco/backends/sql/test_sql.py
raco/datalog/__init__.py
raco/datalog/datalog_test.py
raco/datalog/grammar.py
raco/datalog/model.py
raco/datalog/query_tests.py
raco/datastructure/UnionFind.py
raco/datastructure/__init__.py
raco/datastructure/test_union_find.py
raco/expression/__init__.py
raco/expression/aggregate.py
raco/expression/boolean.py
raco/expression/expression.py
raco/expression/expressions_library.py
raco/expression/function.py
raco/expression/statevar.py
raco/expression/udf.py
raco/expression/util.py
raco/expression/visitor.py
raco/myrial/__init__.py
raco/myrial/cfg.py
raco/myrial/cfg_test.py
raco/myrial/cli_test.py
raco/myrial/emitarg.py
raco/myrial/empty_aggregate_tests.py
raco/myrial/exceptions.py
raco/myrial/filescan_tests.py
raco/myrial/groupby.py
raco/myrial/interpreter.py
raco-1.3.7.dist-info/DESCRIPTION.rst
raco-1.3.7.dist-info/METADATA
raco-1.3.7.dist-info/RECORD
raco-1.3.7.dist-info/WHEEL
raco-1.3.7.dist-info/metadata.json
raco-1.3.7.dist-info/pbr.json
raco-1.3.7.dist-info/top_level.txt
