Metadata-Version: 2.0
Name: raco
Version: 1.3.7
Summary: Relational Algebra COmpiler
Home-page: https://github.com/uwescience/raco
Author: Bill Howe, Andrew Whitaker, Daniel Halperin
Author-email: raco@cs.washington.edu
License: UNKNOWN
Platform: UNKNOWN
Requires-Dist: SQLAlchemy
Requires-Dist: jinja2
Requires-Dist: networkx (==1.11)
Requires-Dist: ply
Requires-Dist: pyparsing
Requires-Dist: requests
Requires-Dist: requests-toolbelt
